hypr_sqlalchemy-0.2.1-py3.5-nspkg.pth
hypr/sqlalchemy.py
hypr_sqlalchemy-0.2.1.dist-info/DESCRIPTION.rst
hypr_sqlalchemy-0.2.1.dist-info/METADATA
hypr_sqlalchemy-0.2.1.dist-info/RECORD
hypr_sqlalchemy-0.2.1.dist-info/WHEEL
hypr_sqlalchemy-0.2.1.dist-info/entry_points.txt
hypr_sqlalchemy-0.2.1.dist-info/metadata.json
hypr_sqlalchemy-0.2.1.dist-info/namespace_packages.txt
hypr_sqlalchemy-0.2.1.dist-info/top_level.txt
